setup.cfg
setup.py
Ramips/Ramips.py
Ramips/__init__.py
Ramips.egg-info/PKG-INFO
Ramips.egg-info/SOURCES.txt
Ramips.egg-info/dependency_links.txt
Ramips.egg-info/top_level.txt